fastimage/__init__.py
fastimage/detect.py
fastimage/tests/__init__.py
fastimage/tests/test_sizing.py
fastimage/tests/utils.py
fastimage-2.0.0.data/scripts/fastimage
fastimage-2.0.0.dist-info/DESCRIPTION.rst
fastimage-2.0.0.dist-info/METADATA
fastimage-2.0.0.dist-info/RECORD
fastimage-2.0.0.dist-info/WHEEL
fastimage-2.0.0.dist-info/metadata.json
fastimage-2.0.0.dist-info/top_level.txt
