Metadata-Version: 2.0
Name: fastimage
Version: 2.0.0
Summary: Finds the size or type of an image given its uri by fetching as little as needed
Home-page: http://github.com/bmuller/fastimage
Author: Brian Muller
Author-email: bamuller@gmail.com
License: MIT
Platform: UNKNOWN
Requires-Dist: aiohttp (>=2.1.0)
